Metadata-Version: 2.1
Name: lusid-sdk-preview
Version: 1.1.257
Summary: Python Preview SDK for LUSID API
Home-page: https://github.com/finbourne/lusid-sdk-python-preview
Author: FINBOURNE Technology
Author-email: engineering@finbourne.com
License: MIT
Keywords: OpenAPI,FINBOURNE,LUSID,LUSID API
Platform: UNKNOWN
Requires-Python: >=3.7
Requires-Dist: certifi (>=14.05.14)
Requires-Dist: six (>=1.10)
Requires-Dist: python-dateutil (>=2.5.3)
Requires-Dist: urllib3 (>=1.26.9)
Requires-Dist: requests (>=2.27.1)
Requires-Dist: pytz (>=2019.1)
